ultimate_mock_wrapper/__init__.py
ultimate_mock_wrapper/base_wrapper.py
ultimate_mock_wrapper/cacheable_meta_type.py
ultimate_mock_wrapper/list_mock.py
ultimate_mock_wrapper-0.0.5.dist-info/LICENSE.txt
ultimate_mock_wrapper-0.0.5.dist-info/METADATA
ultimate_mock_wrapper-0.0.5.dist-info/WHEEL
ultimate_mock_wrapper-0.0.5.dist-info/top_level.txt
ultimate_mock_wrapper-0.0.5.dist-info/RECORD
